cprint/__init__.py
cprint/config.py
cprint/main.py
cprint/tools.py
cprint_jianjun-1.8.0.dist-info/licenses/LICENSE
cprint_jianjun-1.8.0.dist-info/METADATA
cprint_jianjun-1.8.0.dist-info/WHEEL
cprint_jianjun-1.8.0.dist-info/entry_points.txt
cprint_jianjun-1.8.0.dist-info/top_level.txt
cprint_jianjun-1.8.0.dist-info/RECORD
