Metadata-Version: 2.4
Name: cprint-jianjun
Version: 1.8.0
Summary: Colorful Print 彩色文本格式化, 彩色文本输出, 控制打印字符颜色样式!
Home-page: https://github.com/EVA-JianJun/cprint
Author: jianjun
Author-email: 910667956@qq.com
License-File: LICENSE
Requires-Dist: forbiddenfruit>=0.1.4
Dynamic: author
Dynamic: author-email
Dynamic: description
Dynamic: description-content-type
Dynamic: home-page
Dynamic: license-file
Dynamic: requires-dist
Dynamic: summary
